{"asenders": 1912, "asenders_30": 140, "asenders_365": 1490, "asenders_7": 53, "asent": 7798, "asent_30": 352, "asent_365": 5665, "asent_7": 97, "csenders": 906, "csenders_30": 81, "csenders_365": 796, "csenders_7": 30, "csent": 4028, "csent_30": 204, "csent_365": 3564, "csent_7": 50, "diff_netasenders_30": -45, "diff_netasenders_365": 528, "diff_netasenders_7": 10, "diff_netasent_30": -100, "diff_netasent_365": 1538, "diff_netasent_7": 14, "diff_netcsenders_30": -20, "diff_netcsenders_365": 634, "diff_netcsenders_7": 14, "diff_netcsent_30": -161, "diff_netcsent_365": 3067, "diff_netcsent_7": 20, "diff_netparticipants_30": -2, "diff_netparticipants_365": 1612, "diff_netparticipants_7": 27, "diff_netqsenders_30": 22, "diff_netqsenders_365": 1382, "diff_netqsenders_7": 30, "diff_netqsent_30": -94, "diff_netqsent_365": 3243, "diff_netqsent_7": 38, "first_date": "2010-07-21", "last_date": "2014-08-12", "participants": 3696, "participants_30": 390, "participants_365": 3028, "participants_7": 135, "percentage_asenders_30": 24, "percentage_asenders_365": 54, "percentage_asenders_7": 23, "percentage_asent_30": 22, "percentage_asent_365": 37, "percentage_asent_7": 16, "percentage_csenders_30": 19, "percentage_csenders_365": 391, "percentage_csenders_7": 87, "percentage_csent_30": 44, "percentage_csent_365": 617, "percentage_csent_7": 66, "percentage_participants_30": 0, "percentage_participants_365": 113, "percentage_participants_7": 25, "percentage_qsenders_30": 7, "percentage_qsenders_365": 135, "percentage_qsenders_7": 44, "percentage_qsent_30": 17, "percentage_qsent_365": 172, "percentage_qsent_7": 45, "qsenders": 2930, "qsenders_30": 302, "qsenders_365": 2404, "qsenders_7": 97, "qsent": 6367, "qsent_30": 451, "qsent_365": 5127, "qsent_7": 122}