{"actions": 4744, "added_lines": 99564.0, "added_lines_30": 204781, "added_lines_365": 8281498, "added_lines_7": 40557, "authors": 28, "authors_30": 7, "authors_365": 23, "authors_7": 2, "avg_commits_author": 30.3333, "avg_commits_month": 48.1765, "avg_files_author": 57.1852, "avg_files_month": 90.8235, "branches": 4, "commits": 819, "commits_30": 18, "commits_365": 623, "commits_7": 2, "committers": 27, "diff_netadded_lines_30": -89038, "diff_netadded_lines_365": 2003720, "diff_netadded_lines_7": -2925, "diff_netauthors_30": 2, "diff_netauthors_365": 11, "diff_netauthors_7": -3, "diff_netcommits_30": -7, "diff_netcommits_365": 427, "diff_netcommits_7": -7, "diff_netfiles_30": -13, "diff_netfiles_365": -961, "diff_netfiles_7": -22, "diff_netremoved_lines_30": -52038, "diff_netremoved_lines_365": 6163937, "diff_netremoved_lines_7": -42766, "files": 1544, "files_30": 29, "files_365": 303, "files_7": 4, "first_date": "2013-04-15", "last_date": "2014-10-08", "percentage_added_lines_30": 30, "percentage_added_lines_365": 31, "percentage_added_lines_7": 6, "percentage_authors_30": 40, "percentage_authors_365": 91, "percentage_authors_7": 60, "percentage_commits_30": 28, "percentage_commits_365": 217, "percentage_commits_7": 77, "percentage_files_30": 30, "percentage_files_365": 76, "percentage_files_7": 84, "percentage_removed_lines_30": 23, "percentage_removed_lines_365": 168, "percentage_removed_lines_7": 66, "removed_lines": 80781.0, "removed_lines_30": 166088, "removed_lines_365": 9832541, "removed_lines_7": 21667, "repositories": 1}