{"asenders": 1509, "asenders_30": 77, "asenders_365": 1435, "asenders_7": 33, "asent": 5601, "asent_30": 139, "asent_365": 5357, "asent_7": 43, "csenders": 717, "csenders_30": 28, "csenders_365": 697, "csenders_7": 13, "csent": 3153, "csent_30": 86, "csent_365": 3079, "csent_7": 24, "diff_netasenders_30": -106, "diff_netasenders_365": 1286, "diff_netasenders_7": -2, "diff_netasent_30": -293, "diff_netasent_365": 5076, "diff_netasent_7": -20, "diff_netcsenders_30": -75, "diff_netcsenders_365": 663, "diff_netcsenders_7": 0, "diff_netcsent_30": -225, "diff_netcsent_365": 3002, "diff_netcsent_7": -17, "diff_netparticipants_30": -64, "diff_netparticipants_365": 1730, "diff_netparticipants_7": -7, "diff_netqsenders_30": -154, "diff_netqsenders_365": 1983, "diff_netqsenders_7": -27, "diff_netqsent_30": -251, "diff_netqsent_365": 4251, "diff_netqsent_7": -32, "first_date": "2010-07-21", "last_date": "2014-07-14", "participants": 3478, "participants_30": 387, "participants_365": 2999, "participants_7": 120, "percentage_asenders_30": 57, "percentage_asenders_365": 863, "percentage_asenders_7": 5, "percentage_asent_30": 67, "percentage_asent_365": 1806, "percentage_asent_7": 31, "percentage_csenders_30": 72, "percentage_csenders_365": 1950, "percentage_csenders_7": 0, "percentage_csent_30": 72, "percentage_csent_365": 3898, "percentage_csent_7": 41, "percentage_participants_30": 14, "percentage_participants_365": 136, "percentage_participants_7": 5, "percentage_qsenders_30": 59, "percentage_qsenders_365": 1133, "percentage_qsenders_7": 44, "percentage_qsent_30": 63, "percentage_qsent_365": 1950, "percentage_qsent_7": 42, "qsenders": 2262, "qsenders_30": 106, "qsenders_365": 2158, "qsenders_7": 34, "qsent": 4664, "qsent_30": 143, "qsent_365": 4469, "qsent_7": 43}