{"asenders": 162, "asenders_30": 26, "asenders_365": 101, "asenders_7": 7, "asent": 311, "asent_30": 37, "asent_365": 194, "asent_7": 11, "csenders": 65, "csenders_30": 12, "csenders_365": 57, "csenders_7": 5, "csent": 162, "csent_30": 23, "csent_365": 146, "csent_7": 7, "diff_netasenders_30": 3, "diff_netasenders_365": 12, "diff_netasenders_7": -10, "diff_netasent_30": -3, "diff_netasent_365": 38, "diff_netasent_7": -10, "diff_netcsenders_30": 0, "diff_netcsenders_365": 45, "diff_netcsenders_7": -3, "diff_netcsent_30": 6, "diff_netcsent_365": 128, "diff_netcsent_7": -9, "diff_netparticipants_30": 89, "diff_netparticipants_365": 1208, "diff_netparticipants_7": -11, "diff_netqsenders_30": -2, "diff_netqsenders_365": 105, "diff_netqsenders_7": -7, "diff_netqsent_30": -2, "diff_netqsent_365": 209, "diff_netqsent_7": -9, "first_date": "2010-07-21", "last_date": "2014-12-03", "participants": 4526, "participants_30": 463, "participants_365": 3194, "participants_7": 154, "percentage_asenders_30": 13, "percentage_asenders_365": 13, "percentage_asenders_7": 58, "percentage_asent_30": 7, "percentage_asent_365": 24, "percentage_asent_7": 47, "percentage_csenders_30": 0, "percentage_csenders_365": 375, "percentage_csenders_7": 37, "percentage_csent_30": 35, "percentage_csent_365": 711, "percentage_csent_7": 56, "percentage_participants_30": 23, "percentage_participants_365": 60, "percentage_participants_7": 6, "percentage_qsenders_30": 5, "percentage_qsenders_365": 172, "percentage_qsenders_7": 46, "percentage_qsent_30": 5, "percentage_qsent_365": 258, "percentage_qsent_7": 52, "qsenders": 209, "qsenders_30": 34, "qsenders_365": 166, "qsenders_7": 8, "qsent": 352, "qsent_30": 38, "qsent_365": 290, "qsent_7": 8}