{"asenders": 142, "asenders_30": 19, "asenders_365": 81, "asenders_7": 5, "asent": 264, "asent_30": 39, "asent_365": 147, "asent_7": 5, "csenders": 58, "csenders_30": 14, "csenders_365": 52, "csenders_7": 1, "csent": 132, "csent_30": 19, "csent_365": 119, "csent_7": 1, "diff_netasenders_30": 5, "diff_netasenders_365": -14, "diff_netasenders_7": -3, "diff_netasent_30": 21, "diff_netasent_365": -17, "diff_netasent_7": -7, "diff_netcsenders_30": 2, "diff_netcsenders_365": 42, "diff_netcsenders_7": -3, "diff_netcsent_30": -15, "diff_netcsent_365": 104, "diff_netcsent_7": -3, "diff_netparticipants_30": -61, "diff_netparticipants_365": 1336, "diff_netparticipants_7": 1, "diff_netqsenders_30": 17, "diff_netqsenders_365": 67, "diff_netqsenders_7": -8, "diff_netqsent_30": 22, "diff_netqsent_365": 158, "diff_netqsent_7": -9, "first_date": "2010-07-21", "last_date": "2014-10-28", "participants": 4238, "participants_30": 359, "participants_365": 3134, "participants_7": 126, "percentage_asenders_30": 35, "percentage_asenders_365": 14, "percentage_asenders_7": 37, "percentage_asent_30": 116, "percentage_asent_365": 10, "percentage_asent_7": 58, "percentage_csenders_30": 16, "percentage_csenders_365": 420, "percentage_csenders_7": 75, "percentage_csent_30": 44, "percentage_csent_365": 693, "percentage_csent_7": 75, "percentage_participants_30": 14, "percentage_participants_365": 74, "percentage_participants_7": 0, "percentage_qsenders_30": 77, "percentage_qsenders_365": 103, "percentage_qsenders_7": 72, "percentage_qsent_30": 88, "percentage_qsent_365": 185, "percentage_qsent_7": 75, "qsenders": 177, "qsenders_30": 39, "qsenders_365": 132, "qsenders_7": 3, "qsent": 306, "qsent_30": 47, "qsent_365": 243, "qsent_7": 3}