{"actions": 45, "added_lines": 786.0, "added_lines_30": 124180, "added_lines_365": 7901309, "added_lines_7": 5442, "authors": 1, "authors_30": 0, "authors_365": 1, "authors_7": 0, "avg_commits_author": 6.0, "avg_commits_month": 0.4286, "avg_files_author": 26.0, "avg_files_month": 1.8571, "branches": 2, "commits": 6, "commits_30": 0, "commits_365": 2, "commits_7": 0, "committers": 1, "diff_netadded_lines_30": -167428, "diff_netadded_lines_365": 1347407, "diff_netadded_lines_7": -7030, "diff_netauthors_30": 0, "diff_netauthors_365": 0, "diff_netauthors_7": 0, "diff_netcommits_30": 0, "diff_netcommits_365": -8, "diff_netcommits_7": 0, "diff_netfiles_30": 0, "diff_netfiles_365": -45, "diff_netfiles_7": 0, "diff_netremoved_lines_30": 53952, "diff_netremoved_lines_365": 6067294, "diff_netremoved_lines_7": -110960, "files": 26, "files_30": 0, "files_365": 3, "files_7": 0, "first_date": "2013-04-15", "last_date": "2014-10-21", "percentage_added_lines_30": 57, "percentage_added_lines_365": 20, "percentage_added_lines_7": 56, "percentage_authors_30": 0, "percentage_authors_365": 0, "percentage_authors_7": 0, "percentage_commits_30": 0, "percentage_commits_365": 80, "percentage_commits_7": 0, "percentage_files_30": 0, "percentage_files_365": 93, "percentage_files_7": 0, "percentage_removed_lines_30": 33, "percentage_removed_lines_365": 163, "percentage_removed_lines_7": 99, "removed_lines": 188.0, "removed_lines_30": 216725, "removed_lines_365": 9777933, "removed_lines_7": 439, "repositories": 2}