{"asenders": 663, "asenders_30": 149, "asenders_365": 315, "asenders_7": 31, "asent": 2068, "asent_30": 366, "asent_365": 752, "asent_7": 60, "csenders": 275, "csenders_30": 92, "csenders_365": 191, "csenders_7": 13, "csent": 877, "csent_30": 316, "csent_365": 617, "csent_7": 53, "diff_netasenders_30": 63, "diff_netasenders_365": -531, "diff_netasenders_7": 6, "diff_netasent_30": 205, "diff_netasent_365": -2733, "diff_netasent_7": 13, "diff_netcsenders_30": 16, "diff_netcsenders_365": 77, "diff_netcsenders_7": -7, "diff_netcsent_30": 131, "diff_netcsent_365": 329, "diff_netcsent_7": 8, "diff_netparticipants_30": -64, "diff_netparticipants_365": 1730, "diff_netparticipants_7": -7, "diff_netqsenders_30": 111, "diff_netqsenders_365": -353, "diff_netqsenders_7": 19, "diff_netqsent_30": 319, "diff_netqsent_365": -604, "diff_netqsent_7": -41, "first_date": "2010-07-21", "last_date": "2014-07-14", "participants": 3478, "participants_30": 387, "participants_365": 2999, "participants_7": 120, "percentage_asenders_30": 73, "percentage_asenders_365": 62, "percentage_asenders_7": 24, "percentage_asent_30": 127, "percentage_asent_365": 78, "percentage_asent_7": 27, "percentage_csenders_30": 21, "percentage_csenders_365": 67, "percentage_csenders_7": 35, "percentage_csent_30": 70, "percentage_csent_365": 114, "percentage_csent_7": 17, "percentage_participants_30": 14, "percentage_participants_365": 136, "percentage_participants_7": 5, "percentage_qsenders_30": 78, "percentage_qsenders_365": 43, "percentage_qsenders_7": 35, "percentage_qsent_30": 183, "percentage_qsent_365": 43, "percentage_qsent_7": 27, "qsenders": 875, "qsenders_30": 252, "qsenders_365": 463, "qsenders_7": 72, "qsent": 1504, "qsent_30": 493, "qsent_365": 798, "qsent_7": 107}