{"actions": 7534, "added_lines": 916578.0, "added_lines_30": 3264, "added_lines_365": 5249557, "added_lines_7": 146, "authors": 129, "authors_30": 1, "authors_365": 119, "authors_7": 0, "avg_commits_author": 13.7519, "avg_commits_month": 136.4615, "avg_files_author": 12.2636, "avg_files_month": 121.6923, "branches": 7, "commits": 1774, "commits_30": 8, "commits_365": 1435, "commits_7": 0, "committers": 129, "diff_netadded_lines_30": 289, "diff_netadded_lines_365": 1235947, "diff_netadded_lines_7": -292, "diff_netauthors_30": -8, "diff_netauthors_365": 72, "diff_netauthors_7": 0, "diff_netcommits_30": -5, "diff_netcommits_365": 177, "diff_netcommits_7": 0, "diff_netfiles_30": -10, "diff_netfiles_365": 630, "diff_netfiles_7": 0, "diff_netremoved_lines_30": -336, "diff_netremoved_lines_365": -63176, "diff_netremoved_lines_7": -92, "files": 1582, "files_30": 10, "files_365": 1252, "files_7": 0, "first_date": "2013-04-15", "last_date": "2014-07-10", "percentage_added_lines_30": 9, "percentage_added_lines_365": 30, "percentage_added_lines_7": 66, "percentage_authors_30": 88, "percentage_authors_365": 153, "percentage_authors_7": 0, "percentage_commits_30": 38, "percentage_commits_365": 14, "percentage_commits_7": 0, "percentage_files_30": 50, "percentage_files_365": 101, "percentage_files_7": 0, "percentage_removed_lines_30": 20, "percentage_removed_lines_365": 2, "percentage_removed_lines_7": 46, "removed_lines": 423045.0, "removed_lines_30": 1311, "removed_lines_365": 2590149, "removed_lines_7": 105, "repositories": 1}