{"actions": 15, "added_lines": 1125.0, "added_lines_30": 2372, "added_lines_365": 5162172, "added_lines_7": 146, "authors": 1, "authors_30": 0, "authors_365": 1, "authors_7": 0, "avg_commits_author": 3.0, "avg_commits_month": 1.5, "avg_files_author": 8.0, "avg_files_month": 4.0, "branches": 1, "commits": 3, "commits_30": 0, "commits_365": 1, "commits_7": 0, "committers": 1, "diff_netadded_lines_30": -1418, "diff_netadded_lines_365": 1072906, "diff_netadded_lines_7": -36, "diff_netauthors_30": 0, "diff_netauthors_365": 0, "diff_netauthors_7": 0, "diff_netcommits_30": 0, "diff_netcommits_365": -1, "diff_netcommits_7": 0, "diff_netfiles_30": 0, "diff_netfiles_365": -5, "diff_netfiles_7": 0, "diff_netremoved_lines_30": -1039, "diff_netremoved_lines_365": -185145, "diff_netremoved_lines_7": 74, "files": 8, "files_30": 0, "files_365": 3, "files_7": 0, "first_date": "2013-04-15", "last_date": "2014-07-10", "percentage_added_lines_30": 37, "percentage_added_lines_365": 26, "percentage_added_lines_7": 19, "percentage_authors_30": 0, "percentage_authors_365": 0, "percentage_authors_7": 0, "percentage_commits_30": 0, "percentage_commits_365": 50, "percentage_commits_7": 0, "percentage_files_30": 0, "percentage_files_365": 62, "percentage_files_7": 0, "percentage_removed_lines_30": 52, "percentage_removed_lines_365": 6, "percentage_removed_lines_7": 238, "removed_lines": 104.0, "removed_lines_30": 937, "removed_lines_365": 2525488, "removed_lines_7": 105, "repositories": 1}