{"authors.": {"authors": ["Jenkins", "Matthias Runge", "Akihiro MOTOKI", "OpenStack Proposal Bot", "Julie Pichon", "Zhenguo Niu", "Lin Hua Cheng", "David Lyle", "Radomir Dopieralski", "Tatiana Mazur"], "commits": [340, 124, 109, 64, 60, 59, 52, 49, 46, 39], "id": [26, 537, 78, 862, 663, 183, 422, 541, 1903, 1865]}, "authors.last month": {"authors": ["Jenkins", "Matthias Runge", "OpenStack Proposal Bot", "Akihiro MOTOKI", "Lin Hua Cheng", "Bradley Jones", "Gloria Gu", "Julie Pichon", "Radomir Dopieralski", "Sam Betts"], "commits": [22, 12, 12, 8, 4, 3, 3, 3, 3, 3], "id": [26, 537, 862, 78, 422, 1870, 332033, 663, 1903, 427458]}, "authors.last year": {"authors": ["Jenkins", "Matthias Runge", "Akihiro MOTOKI", "OpenStack Proposal Bot", "Radomir Dopieralski", "Zhenguo Niu", "Julie Pichon", "Lin Hua Cheng", "David Lyle", "Cindy Lu"], "commits": [280, 115, 87, 64, 46, 41, 39, 36, 34, 28], "id": [26, 537, 78, 862, 1903, 183, 663, 422, 541, 331991]}}