{"asenders": 1474, "asenders_30": 101, "asenders_365": 1404, "asenders_7": 34, "asent": 5484, "asent_30": 171, "asent_365": 5252, "asent_7": 55, "csenders": 698, "csenders_30": 38, "csenders_365": 679, "csenders_7": 8, "csent": 3041, "csent_30": 107, "csent_365": 2976, "csent_7": 30, "diff_netasenders_30": -76, "diff_netasenders_365": 1263, "diff_netasenders_7": 31, "diff_netasent_30": -260, "diff_netasent_365": 4983, "diff_netasent_7": 52, "diff_netcsenders_30": -79, "diff_netcsenders_365": 648, "diff_netcsenders_7": 7, "diff_netcsent_30": -276, "diff_netcsent_365": 2908, "diff_netcsent_7": 29, "diff_netparticipants_30": -18, "diff_netparticipants_365": 1760, "diff_netparticipants_7": -14, "diff_netqsenders_30": -146, "diff_netqsenders_365": 1978, "diff_netqsenders_7": 47, "diff_netqsent_30": -281, "diff_netqsent_365": 4178, "diff_netqsent_7": 57, "first_date": "2010-07-21", "last_date": "2014-07-04", "participants": 3419, "participants_30": 429, "participants_365": 2988, "participants_7": 132, "percentage_asenders_30": 42, "percentage_asenders_365": 895, "percentage_asenders_7": 1033, "percentage_asent_30": 60, "percentage_asent_365": 1852, "percentage_asent_7": 1733, "percentage_csenders_30": 67, "percentage_csenders_365": 2090, "percentage_csenders_7": 700, "percentage_csent_30": 72, "percentage_csent_365": 4276, "percentage_csent_7": 2900, "percentage_participants_30": 4, "percentage_participants_365": 143, "percentage_participants_7": 9, "percentage_qsenders_30": 53, "percentage_qsenders_365": 1276, "percentage_qsenders_7": 940, "percentage_qsent_30": 63, "percentage_qsent_365": 2222, "percentage_qsent_7": 1140, "qsenders": 2221, "qsenders_30": 126, "qsenders_365": 2133, "qsenders_7": 52, "qsent": 4531, "qsent_30": 160, "qsent_365": 4366, "qsent_7": 62}