{"asenders": 1508, "asenders_30": 92, "asenders_365": 1411, "asenders_7": 43, "asent": 5568, "asent_30": 157, "asent_365": 5251, "asent_7": 61, "csenders": 723, "csenders_30": 47, "csenders_365": 700, "csenders_7": 29, "csent": 3120, "csent_30": 112, "csent_365": 3024, "csent_7": 51, "diff_netasenders_30": -16, "diff_netasenders_365": 1226, "diff_netasenders_7": 37, "diff_netasent_30": -47, "diff_netasent_365": 4897, "diff_netasent_7": 54, "diff_netcsenders_30": -8, "diff_netcsenders_365": 656, "diff_netcsenders_7": 23, "diff_netcsent_30": -40, "diff_netcsent_365": 2925, "diff_netcsent_7": 42, "diff_netparticipants_30": -46, "diff_netparticipants_365": 1685, "diff_netparticipants_7": -14, "diff_netqsenders_30": 19, "diff_netqsenders_365": 1919, "diff_netqsenders_7": 60, "diff_netqsent_30": 14, "diff_netqsent_365": 4065, "diff_netqsent_7": 69, "first_date": "2010-07-21", "last_date": "2014-07-26", "participants": 3582, "participants_30": 401, "participants_365": 3024, "participants_7": 128, "percentage_asenders_30": 14, "percentage_asenders_365": 662, "percentage_asenders_7": 616, "percentage_asent_30": 23, "percentage_asent_365": 1383, "percentage_asent_7": 771, "percentage_csenders_30": 14, "percentage_csenders_365": 1490, "percentage_csenders_7": 383, "percentage_csent_30": 26, "percentage_csent_365": 2954, "percentage_csent_7": 466, "percentage_participants_30": 10, "percentage_participants_365": 125, "percentage_participants_7": 9, "percentage_qsenders_30": 13, "percentage_qsenders_365": 845, "percentage_qsenders_7": 428, "percentage_qsent_30": 7, "percentage_qsent_365": 1337, "percentage_qsent_7": 405, "qsenders": 2287, "qsenders_30": 156, "qsenders_365": 2146, "qsenders_7": 74, "qsent": 4650, "qsent_30": 197, "qsent_365": 4369, "qsent_7": 86}