{"actions": 16530, "added_lines": 371720.0, "added_lines_30": 195389, "added_lines_365": 8209987, "added_lines_7": 37410, "authors": 142, "authors_30": 37, "authors_365": 122, "authors_7": 2, "avg_commits_author": 28.1056, "avg_commits_month": 234.7647, "avg_files_author": 46.6972, "avg_files_month": 390.0588, "branches": 17, "commits": 3991, "commits_30": 169, "commits_365": 2704, "commits_7": 2, "committers": 138, "diff_netadded_lines_30": -109198, "diff_netadded_lines_365": 1878679, "diff_netadded_lines_7": -935, "diff_netauthors_30": -14, "diff_netauthors_365": 38, "diff_netauthors_7": -9, "diff_netcommits_30": -102, "diff_netcommits_365": 550, "diff_netcommits_7": -16, "diff_netfiles_30": -680, "diff_netfiles_365": 783, "diff_netfiles_7": -35, "diff_netremoved_lines_30": -62875, "diff_netremoved_lines_365": 6089915, "diff_netremoved_lines_7": -39645, "files": 6631, "files_30": 393, "files_365": 5258, "files_7": 3, "first_date": "2013-04-15", "last_date": "2014-10-09", "percentage_added_lines_30": 35, "percentage_added_lines_365": 29, "percentage_added_lines_7": 2, "percentage_authors_30": 27, "percentage_authors_365": 45, "percentage_authors_7": 81, "percentage_commits_30": 37, "percentage_commits_365": 25, "percentage_commits_7": 88, "percentage_files_30": 63, "percentage_files_365": 17, "percentage_files_7": 92, "percentage_removed_lines_30": 28, "percentage_removed_lines_365": 164, "percentage_removed_lines_7": 68, "removed_lines": 158720.0, "removed_lines_30": 160720, "removed_lines_365": 9787304, "removed_lines_7": 18367, "repositories": 21}