{"asenders": 60, "asenders_30": 6, "asenders_365": 53, "asenders_7": 1, "asent": 73, "asent_30": 7, "asent_365": 64, "asent_7": 1, "csenders": 26, "csenders_30": 1, "csenders_365": 26, "csenders_7": 1, "csent": 42, "csent_30": 1, "csent_365": 42, "csent_7": 1, "diff_netasenders_30": 1, "diff_netasenders_365": 44, "diff_netasenders_7": 0, "diff_netasent_30": -1, "diff_netasent_365": 53, "diff_netasent_7": 0, "diff_netcsenders_30": -1, "diff_netcsenders_365": 24, "diff_netcsenders_7": 1, "diff_netcsent_30": -3, "diff_netcsent_365": 40, "diff_netcsent_7": 1, "diff_netparticipants_30": -38, "diff_netparticipants_365": 1708, "diff_netparticipants_7": 13, "diff_netqsenders_30": -3, "diff_netqsenders_365": 35, "diff_netqsenders_7": 0, "diff_netqsent_30": -3, "diff_netqsent_365": 40, "diff_netqsent_7": 0, "first_date": "2010-07-21", "last_date": "2014-07-21", "participants": 3540, "participants_30": 394, "participants_365": 3016, "participants_7": 133, "percentage_asenders_30": 20, "percentage_asenders_365": 488, "percentage_asenders_7": 0, "percentage_asent_30": 12, "percentage_asent_365": 481, "percentage_asent_7": 0, "percentage_csenders_30": 50, "percentage_csenders_365": 1200, "percentage_csenders_7": 0, "percentage_csent_30": 75, "percentage_csent_365": 2000, "percentage_csent_7": 0, "percentage_participants_30": 8, "percentage_participants_365": 130, "percentage_participants_7": 10, "percentage_qsenders_30": 50, "percentage_qsenders_365": 388, "percentage_qsenders_7": 0, "percentage_qsent_30": 50, "percentage_qsent_365": 444, "percentage_qsent_7": 0, "qsenders": 51, "qsenders_30": 3, "qsenders_365": 44, "qsenders_7": 1, "qsent": 56, "qsent_30": 3, "qsent_365": 49, "qsent_7": 1}