{"allhistory_participants": 676, "changed": 745, "changed_30": 97, "changed_365": 691, "changed_7": 51, "changers": 277, "changers_30": 65, "changers_365": 253, "changers_7": 24, "closed": 421, "closed_30": 52, "closed_365": 366, "closed_7": 33, "closers": 82, "closers_30": 19, "closers_365": 70, "closers_7": 8, "companies": 8, "diff_netchanged_30": -17, "diff_netchanged_365": 488, "diff_netchanged_7": 18, "diff_netchangers_30": 14, "diff_netchangers_365": 155, "diff_netchangers_7": -4, "diff_netclosed_30": 8, "diff_netclosed_365": 311, "diff_netclosed_7": 24, "diff_netclosers_30": 3, "diff_netclosers_365": 43, "diff_netclosers_7": 0, "diff_netopened_30": -8, "diff_netopened_365": 314, "diff_netopened_7": 8, "diff_netopeners_30": -10, "diff_netopeners_365": 76, "diff_netopeners_7": 6, "first_date": "2013-04-16", "last_date": "2014-10-31", "opened": 783, "opened_30": 53, "opened_365": 551, "opened_7": 16, "openers": 199, "openers_30": 27, "openers_365": 159, "openers_7": 12, "percentage_changed_30": 14, "percentage_changed_365": 240, "percentage_changed_7": 54, "percentage_changers_30": 27, "percentage_changers_365": 158, "percentage_changers_7": 14, "percentage_closed_30": 18, "percentage_closed_365": 565, "percentage_closed_7": 266, "percentage_closers_30": 18, "percentage_closers_365": 159, "percentage_closers_7": 0, "percentage_opened_30": 13, "percentage_opened_365": 132, "percentage_opened_7": 100, "percentage_openers_30": 27, "percentage_openers_365": 91, "percentage_openers_7": 100, "trackers": 1, "type": "bugzilla", "url": "https://bugzilla.redhat.com/buglist.cgi?product=RDO"}