{"closers.": {"closed": [45, 41, 39, 25, 17, 13, 11, 10, 9, 9], "closers": ["Martin Magr", "Matthias Runge", "P\u00e1draig Brady", "Lars Kellogg-Stedman", "Xavier Queralt", "Alan Pevec", "Jeff Peeler", "Jakub Ruzicka", "Kashyap Chamarthy", "Stephen Gordon"], "id": [1937, 1989, 1919, 2094, 2024, 1918, 1923, 1948, 1917, 2000]}, "closers.last month": {"closed": [4, 4, 3, 3, 3, 2, 2, 1, 1, 1], "closers": ["Alan Pevec", "Jason Guiditta", "Lars Kellogg-Stedman", "Lon Hohberger", "Matthias Runge", "Eric Harney", "Lukas Bezdicka", "Ha\u00efkel Gu\u00e9mar", "Jeff Peeler", "Kashyap Chamarthy"], "id": [1918, 2137, 2094, 1966, 1989, 1968, 2307, 427495, 1923, 1917]}, "closers.last year": {"closed": [41, 40, 32, 25, 16, 10, 10, 9, 8, 8], "closers": ["Martin Magr", "Matthias Runge", "P\u00e1draig Brady", "Lars Kellogg-Stedman", "Xavier Queralt", "Alan Pevec", "Jakub Ruzicka", "Stephen Gordon", "Jakub Libosvar", "Jeff Peeler"], "id": [1937, 1989, 1919, 2094, 2024, 1918, 1948, 2000, 2097, 1923]}, "openers.": {"id": [1543, 780, 1990, 1979, 486509, 2032, 461, 2021, 2026, 2034], "opened": [43, 28, 27, 24, 23, 22, 18, 17, 16, 15], "openers": ["wes hayutin", "Lars Kellogg-Stedman", "Mohammed Arafa", "afazekas", "P\u00e1draig Brady", "Dafna Ron", "Giulio Fidente", "Nir Magnezi", "Yogev Rabl", "Ofer Blaut"]}, "openers.last month": {"id": [1543, 780, 2370, 276179, 126, 1970, 557, 1748, 486532, 2308], "opened": [9, 4, 2, 2, 1, 1, 1, 1, 1, 1], "openers": ["wes hayutin", "Lars Kellogg-Stedman", "b24warbaby", "Dan Sneddon", "Alan Pevec", "Etsuji Nakai", "Jakub Ruzicka", "James Slagle", "KrishnaS", "lbezdick"]}, "openers.last year": {"id": [1543, 780, 1990, 1979, 461, 2026, 2032, 2034, 2021, 486509], "opened": [39, 28, 23, 21, 17, 15, 14, 13, 12, 12], "openers": ["wes hayutin", "Lars Kellogg-Stedman", "Mohammed Arafa", "afazekas", "Giulio Fidente", "Yogev Rabl", "Dafna Ron", "Ofer Blaut", "Nir Magnezi", "P\u00e1draig Brady"]}}