{"actions": 8341, "added_lines": 459670.0, "added_lines_30": 182839, "added_lines_365": 8867834, "added_lines_7": 4612, "authors": 182, "authors_30": 19, "authors_365": 135, "authors_7": 1, "avg_commits_author": 11.2857, "avg_commits_month": 128.375, "avg_files_author": 7.8407, "avg_files_month": 89.1875, "branches": 6, "commits": 2054, "commits_30": 104, "commits_365": 1572, "commits_7": 5, "committers": 166, "diff_netadded_lines_30": -54456, "diff_netadded_lines_365": 3304562, "diff_netadded_lines_7": -8813, "diff_netauthors_30": -16, "diff_netauthors_365": 4, "diff_netauthors_7": -5, "diff_netcommits_30": -57, "diff_netcommits_365": 600, "diff_netcommits_7": -7, "diff_netfiles_30": -57, "diff_netfiles_365": 645, "diff_netfiles_7": -19, "diff_netremoved_lines_30": 12643, "diff_netremoved_lines_365": 6704123, "diff_netremoved_lines_7": -7519, "files": 1427, "files_30": 167, "files_365": 1251, "files_7": 10, "first_date": "2013-04-15", "last_date": "2014-09-15", "percentage_added_lines_30": 22, "percentage_added_lines_365": 59, "percentage_added_lines_7": 65, "percentage_authors_30": 45, "percentage_authors_365": 3, "percentage_authors_7": 83, "percentage_commits_30": 35, "percentage_commits_365": 61, "percentage_commits_7": 58, "percentage_files_30": 25, "percentage_files_365": 106, "percentage_files_7": 65, "percentage_removed_lines_30": 9, "percentage_removed_lines_365": 200, "percentage_removed_lines_7": 95, "removed_lines": 425059.0, "removed_lines_30": 142094, "removed_lines_365": 10048873, "removed_lines_7": 373, "repositories": 1}