{"asenders": 59, "asenders_30": 6, "asenders_365": 55, "asenders_7": 1, "asent": 83, "asent_30": 6, "asent_365": 79, "asent_7": 1, "csenders": 35, "csenders_30": 4, "csenders_365": 35, "csenders_7": 2, "csent": 74, "csent_30": 6, "csent_365": 73, "csent_7": 2, "diff_netasenders_30": -5, "diff_netasenders_365": 47, "diff_netasenders_7": 0, "diff_netasent_30": -8, "diff_netasent_365": 64, "diff_netasent_7": 0, "diff_netcsenders_30": 0, "diff_netcsenders_365": 33, "diff_netcsenders_7": 2, "diff_netcsent_30": 1, "diff_netcsent_365": 70, "diff_netcsent_7": 2, "diff_netparticipants_30": 8, "diff_netparticipants_365": 1246, "diff_netparticipants_7": 24, "diff_netqsenders_30": -4, "diff_netqsenders_365": 68, "diff_netqsenders_7": -1, "diff_netqsent_30": -4, "diff_netqsent_365": 72, "diff_netqsent_7": -1, "first_date": "2010-07-21", "last_date": "2014-11-16", "participants": 4382, "participants_30": 404, "participants_365": 3144, "participants_7": 144, "percentage_asenders_30": 45, "percentage_asenders_365": 587, "percentage_asenders_7": 0, "percentage_asent_30": 57, "percentage_asent_365": 426, "percentage_asent_7": 0, "percentage_csenders_30": 0, "percentage_csenders_365": 1650, "percentage_csenders_7": 0, "percentage_csent_30": 20, "percentage_csent_365": 2333, "percentage_csent_7": 0, "percentage_participants_30": 2, "percentage_participants_365": 65, "percentage_participants_7": 20, "percentage_qsenders_30": 30, "percentage_qsenders_365": 1133, "percentage_qsenders_7": 33, "percentage_qsent_30": 30, "percentage_qsent_365": 1200, "percentage_qsent_7": 33, "qsenders": 78, "qsenders_30": 9, "qsenders_365": 74, "qsenders_7": 2, "qsent": 82, "qsent_30": 9, "qsent_365": 78, "qsent_7": 2}