{"authors": 152, "authors_30": 10, "authors_365": 145, "authors_7": 2, "diff_netauthors_30": -7, "diff_netauthors_365": 113, "diff_netauthors_7": -2, "diff_netreviews_30": -20, "diff_netreviews_365": 1537, "diff_netreviews_7": -15, "first_date": "2013-04-15", "last_date": "2014-07-07", "pages": 88, "percentage_authors_30": 41, "percentage_authors_365": 353, "percentage_authors_7": 50, "percentage_reviews_30": 25, "percentage_reviews_365": 288, "percentage_reviews_7": 71, "reviews": 2229, "reviews_30": 58, "reviews_365": 2070, "reviews_7": 6}