{"authors": 171, "authors_30": 40, "authors_365": 131, "authors_7": 35, "diff_netauthors_30": 32, "diff_netauthors_365": 44, "diff_netauthors_7": 24, "diff_netreviews_30": 164, "diff_netreviews_365": 288, "diff_netreviews_7": 101, "first_date": "2013-04-15", "last_date": "2014-10-07", "pages": 88, "percentage_authors_30": 400, "percentage_authors_365": 50, "percentage_authors_7": 218, "percentage_reviews_30": 348, "percentage_reviews_365": 22, "percentage_reviews_7": 420, "reviews": 2522, "reviews_30": 211, "reviews_365": 1592, "reviews_7": 125}