{"authors.": {"authors": ["Rich Bowen", "Rlandy", "dneary", "Radez", "Ryan Brady", "Pixelbeat", "eglynn", "pmyers", "rkukura", "Rob Crittenden"], "id": [1576, 1966, 1617, 1751, 1855, 1740, 1656, 1621, 1636, 646], "reviews": [572, 129, 117, 86, 78, 69, 64, 58, 56, 43]}, "authors.last month": {"authors": ["Rlandy", "Ryan Brady", "Rich Bowen", "Pixelbeat", "Admiyo", "Tshefi", "Jbainbri", "Kashyap", "Rob", "dansmith"], "id": [1966, 1855, 1576, 1740, 1783, 2007, 2150, 1738, 2141, 1707], "reviews": [121, 78, 51, 15, 5, 5, 4, 4, 3, 2]}, "authors.last year": {"authors": ["Rich Bowen", "Rlandy", "dneary", "Radez", "Ryan Brady", "Pixelbeat", "eglynn", "pmyers", "rkukura", "Rob Crittenden"], "id": [1576, 1966, 1617, 1751, 1855, 1740, 1656, 1621, 1636, 646], "reviews": [572, 129, 104, 86, 78, 69, 64, 58, 56, 43]}}