{"companies": 6, "diff_netsenders_30": 15, "diff_netsenders_365": 144, "diff_netsenders_7": 8, "diff_netsent_30": 67, "diff_netsent_365": 1552, "diff_netsent_7": 17, "first_date": "2013-04-17", "last_date": "2014-07-22", "percentage_senders_30": 40, "percentage_senders_365": 411, "percentage_senders_7": 53, "percentage_sent_30": 55, "percentage_sent_365": 476, "percentage_sent_7": 56, "repositories": 1, "senders": 189, "senders_30": 52, "senders_365": 179, "senders_7": 23, "senders_init": 109, "senders_response": 150, "sent": 2203, "sent_30": 188, "sent_365": 1878, "sent_7": 47, "sent_response": 1048, "threads": 882}