{"companies": 6, "diff_netsenders_30": 5, "diff_netsenders_365": 136, "diff_netsenders_7": 7, "diff_netsent_30": 49, "diff_netsent_365": 1081, "diff_netsent_7": 30, "first_date": "2013-04-17", "last_date": "2014-09-14", "percentage_senders_30": 15, "percentage_senders_365": 272, "percentage_senders_7": 63, "percentage_sent_30": 67, "percentage_sent_365": 168, "percentage_sent_7": 157, "repositories": 1, "senders": 203, "senders_30": 37, "senders_365": 186, "senders_7": 18, "senders_init": 120, "senders_response": 162, "sent": 2366, "sent_30": 122, "sent_365": 1724, "sent_7": 49, "sent_response": 1163, "threads": 1203}