{"actions": 5714, "added_lines": 361398.0, "added_lines_30": 278613, "added_lines_365": 10229592, "added_lines_7": 4251, "authors": 22, "authors_30": 2, "authors_365": 17, "authors_7": 0, "avg_commits_author": 48.2273, "avg_commits_month": 58.9444, "avg_files_author": 149.8636, "avg_files_month": 183.1667, "branches": 15, "commits": 1061, "commits_30": 4, "commits_365": 737, "commits_7": 0, "committers": 22, "diff_netadded_lines_30": 18516, "diff_netadded_lines_365": -266854, "diff_netadded_lines_7": -143341, "diff_netauthors_30": -2, "diff_netauthors_365": 0, "diff_netauthors_7": -2, "diff_netcommits_30": -20, "diff_netcommits_365": 271, "diff_netcommits_7": -2, "diff_netfiles_30": -155, "diff_netfiles_365": 785, "diff_netfiles_7": -2, "diff_netremoved_lines_30": -225902, "diff_netremoved_lines_365": 6582941, "diff_netremoved_lines_7": 496, "files": 3297, "files_30": 3, "files_365": 2410, "files_7": 0, "first_date": "2013-04-15", "last_date": "2014-11-27", "percentage_added_lines_30": 7, "percentage_added_lines_365": 2, "percentage_added_lines_7": 97, "percentage_authors_30": 50, "percentage_authors_365": 0, "percentage_authors_7": 100, "percentage_commits_30": 83, "percentage_commits_365": 58, "percentage_commits_7": 100, "percentage_files_30": 98, "percentage_files_365": 48, "percentage_files_7": 100, "percentage_removed_lines_30": 96, "percentage_removed_lines_365": 106, "percentage_removed_lines_7": 22, "removed_lines": 276113.0, "removed_lines_30": 8695, "removed_lines_365": 12778989, "removed_lines_7": 2684, "repositories": 23}