{"actions": 4957, "added_lines": 289979.0, "added_lines_30": 141560, "added_lines_365": 10587366, "added_lines_7": 6668, "authors": 16, "authors_30": 4, "authors_365": 16, "authors_7": 4, "avg_commits_author": 16.4667, "avg_commits_month": 27.4444, "avg_files_author": 292.2, "avg_files_month": 487.0, "branches": 5, "commits": 247, "commits_30": 82, "commits_365": 247, "commits_7": 33, "committers": 15, "diff_netadded_lines_30": -198154, "diff_netadded_lines_365": 516136, "diff_netadded_lines_7": 5648, "diff_netauthors_30": -2, "diff_netauthors_365": 16, "diff_netauthors_7": 1, "diff_netcommits_30": 40, "diff_netcommits_365": 247, "diff_netcommits_7": 25, "diff_netfiles_30": -148, "diff_netfiles_365": 4383, "diff_netfiles_7": 106, "diff_netremoved_lines_30": -306898, "diff_netremoved_lines_365": 6956907, "diff_netremoved_lines_7": 573, "files": 4383, "files_30": 2220, "files_365": 4383, "files_7": 132, "first_date": "2013-04-15", "last_date": "2014-11-16", "percentage_added_lines_30": 58, "percentage_added_lines_365": 5, "percentage_added_lines_7": 553, "percentage_authors_30": 33, "percentage_authors_365": 0, "percentage_authors_7": 33, "percentage_commits_30": 95, "percentage_commits_365": 0, "percentage_commits_7": 312, "percentage_files_30": 6, "percentage_files_365": 0, "percentage_files_7": 407, "percentage_removed_lines_30": 98, "percentage_removed_lines_365": 115, "percentage_removed_lines_7": 194, "removed_lines": 4175.0, "removed_lines_30": 5014, "removed_lines_365": 12983227, "removed_lines_7": 867, "repositories": 1}