{"actions": 400, "added_lines": 13426.0, "added_lines_30": 53326, "added_lines_365": 7510136, "added_lines_7": 357, "authors": 66, "authors_30": 2, "authors_365": 43, "authors_7": 0, "avg_commits_author": 3.3939, "avg_commits_month": 13.1765, "avg_files_author": 1.303, "avg_files_month": 5.0588, "branches": 5, "commits": 224, "commits_30": 2, "commits_365": 158, "commits_7": 0, "committers": 63, "diff_netadded_lines_30": -159793, "diff_netadded_lines_365": 630341, "diff_netadded_lines_7": 24, "diff_netauthors_30": -4, "diff_netauthors_365": -3, "diff_netauthors_7": 0, "diff_netcommits_30": -8, "diff_netcommits_365": 55, "diff_netcommits_7": 0, "diff_netfiles_30": -10, "diff_netfiles_365": 35, "diff_netfiles_7": 0, "diff_netremoved_lines_30": -49465, "diff_netremoved_lines_365": 5651730, "diff_netremoved_lines_7": 76, "files": 86, "files_30": 3, "files_365": 72, "files_7": 0, "first_date": "2013-04-15", "last_date": "2014-10-29", "percentage_added_lines_30": 74, "percentage_added_lines_365": 9, "percentage_added_lines_7": 7, "percentage_authors_30": 66, "percentage_authors_365": 6, "percentage_authors_7": 0, "percentage_commits_30": 80, "percentage_commits_365": 53, "percentage_commits_7": 0, "percentage_files_30": 76, "percentage_files_365": 94, "percentage_files_7": 0, "percentage_removed_lines_30": 27, "percentage_removed_lines_365": 145, "percentage_removed_lines_7": 380, "removed_lines": 8386.0, "removed_lines_30": 131363, "removed_lines_365": 9535271, "removed_lines_7": 96, "repositories": 1}