{"actions": 400, "added_lines": 13426.0, "added_lines_30": 283818, "added_lines_365": 10480031, "added_lines_7": 144810, "authors": 66, "authors_30": 0, "authors_365": 42, "authors_7": 0, "avg_commits_author": 3.3939, "avg_commits_month": 13.1765, "avg_files_author": 1.303, "avg_files_month": 5.0588, "branches": 5, "commits": 224, "commits_30": 0, "commits_365": 156, "commits_7": 0, "committers": 63, "diff_netadded_lines_30": -10954, "diff_netadded_lines_365": 225456, "diff_netadded_lines_7": 137261, "diff_netauthors_30": -5, "diff_netauthors_365": 0, "diff_netauthors_7": 0, "diff_netcommits_30": -7, "diff_netcommits_365": 57, "diff_netcommits_7": 0, "diff_netfiles_30": -8, "diff_netfiles_365": 35, "diff_netfiles_7": 0, "diff_netremoved_lines_30": -269336, "diff_netremoved_lines_365": 6778555, "diff_netremoved_lines_7": 881, "files": 86, "files_30": 0, "files_365": 72, "files_7": 0, "first_date": "2013-04-15", "last_date": "2014-11-22", "percentage_added_lines_30": 3, "percentage_added_lines_365": 2, "percentage_added_lines_7": 1818, "percentage_authors_30": 100, "percentage_authors_365": 0, "percentage_authors_7": 0, "percentage_commits_30": 100, "percentage_commits_365": 57, "percentage_commits_7": 0, "percentage_files_30": 100, "percentage_files_365": 94, "percentage_files_7": 0, "percentage_removed_lines_30": 97, "percentage_removed_lines_365": 111, "percentage_removed_lines_7": 81, "removed_lines": 8386.0, "removed_lines_30": 6406, "removed_lines_365": 12879035, "removed_lines_7": 1959, "repositories": 1}