{"asenders": 2407, "asenders_30": 193, "asenders_365": 1486, "asenders_7": 52, "asent": 10494, "asent_30": 481, "asent_365": 6060, "asent_7": 117, "csenders": 2056, "csenders_30": 164, "csenders_365": 1466, "csenders_7": 43, "csent": 11521, "csent_30": 560, "csent_365": 8021, "csent_7": 99, "diff_netasenders_30": -5, "diff_netasenders_365": 185, "diff_netasenders_7": 16, "diff_netasent_30": -184, "diff_netasent_365": 612, "diff_netasent_7": 47, "diff_netcsenders_30": -25, "diff_netcsenders_365": 670, "diff_netcsenders_7": 16, "diff_netcsent_30": -186, "diff_netcsent_365": 4446, "diff_netcsent_7": 29, "diff_netparticipants_30": -78, "diff_netparticipants_365": 1028, "diff_netparticipants_7": 25, "diff_netqsenders_30": -63, "diff_netqsenders_365": 1034, "diff_netqsenders_7": 11, "diff_netqsent_30": -104, "diff_netqsent_365": 2800, "diff_netqsent_7": 4, "first_date": "2010-07-21", "last_date": "2015-01-06", "participants": 4758, "participants_30": 398, "participants_365": 3209, "participants_7": 111, "percentage_asenders_30": 2, "percentage_asenders_365": 14, "percentage_asenders_7": 44, "percentage_asent_30": 27, "percentage_asent_365": 11, "percentage_asent_7": 67, "percentage_csenders_30": 13, "percentage_csenders_365": 84, "percentage_csenders_7": 59, "percentage_csent_30": 24, "percentage_csent_365": 124, "percentage_csent_7": 41, "percentage_participants_30": 16, "percentage_participants_365": 47, "percentage_participants_7": 29, "percentage_qsenders_30": 17, "percentage_qsenders_365": 62, "percentage_qsenders_7": 18, "percentage_qsent_30": 17, "percentage_qsent_365": 84, "percentage_qsent_7": 4, "qsenders": 3925, "qsenders_30": 303, "qsenders_365": 2691, "qsenders_7": 72, "qsent": 9076, "qsent_30": 493, "qsent_365": 6119, "qsent_7": 87}