{"asenders.": {"id": [2513, 3070, 9, 1745, 2136, 2408, 3246, 3070, 386, 64], "senders": ["dbaxps", "SGPJ", "smaffulli", "larsks", "mpetason", "SamYaple", "Haneef Ali", "Shankar Ganesh P J", "darragh-oreilly", "fifieldt"], "sent": [83631, 29274, 18500, 15192, 12240, 12191, 11508, 10353, 3654, 3417]}, "asenders.last month": {"id": [2513, 2136, 9, 2408, 2894, 1825, 3246, 8670, 7964, 2571], "senders": ["dbaxps", "mpetason", "smaffulli", "SamYaple", "9lives", "vinoth", "Haneef Ali", "PradeepNaik", "Mzoorikh", "teju"], "sent": [16836, 2992, 1850, 1022, 846, 715, 672, 400, 378, 318]}, "asenders.last year": {"id": [2513, 3070, 1745, 2136, 2408, 3246, 9, 3070, 2894, 7964], "senders": ["dbaxps", "SGPJ", "larsks", "mpetason", "SamYaple", "Haneef Ali", "smaffulli", "Shankar Ganesh P J", "9lives", "Mzoorikh"], "sent": [83631, 29274, 13248, 12172, 11753, 11508, 10952, 10353, 3149, 2688]}, "csenders.": {"id": [2513, 9, 3070, 1745, 2136, 2408, 3070, 386, 3246, 3340], "senders": ["dbaxps", "smaffulli", "SGPJ", "larsks", "mpetason", "SamYaple", "Shankar Ganesh P J", "darragh-oreilly", "Haneef Ali", "Antonio G."], "sent": [188490, 40700, 20254, 18432, 12988, 12775, 7163, 6006, 5292, 4142]}, "csenders.last month": {"id": [2513, 9, 2136, 2894, 2408, 7609, 8436, 6560, 3070, 3340], "senders": ["dbaxps", "smaffulli", "mpetason", "9lives", "SamYaple", "mickt", "patrickt33", "amitabh sinha", "SGPJ", "Antonio G."], "sent": [37149, 2590, 1836, 1081, 876, 702, 418, 352, 328, 266]}, "csenders.last year": {"id": [2513, 9, 3070, 1745, 2136, 2408, 3070, 3246, 3340, 2894], "senders": ["dbaxps", "smaffulli", "SGPJ", "larsks", "mpetason", "SamYaple", "Shankar Ganesh P J", "Haneef Ali", "Antonio G.", "9lives"], "sent": [188490, 26270, 20254, 15624, 12988, 12556, 7163, 5292, 4142, 3807]}, "participants.": {"id": [630911, 630994, 635376, 630817, 631088, 630928, 630918, 1755, 631055, 631114], "messages_sent": [279258, 59422, 51004, 34056, 25296, 25112, 18038, 16800, 9660, 7802], "name": ["dbaxps", "smaffulli", "SGPJ", "larsks", "mpetason", "SamYaple", "Shankar Ganesh P J", "Haneef Ali", "darragh-oreilly", "9lives"]}, "participants.last month": {"id": [630911, 631088, 630994, 631114, 630928, 631056, 635704, 1755, 631151, 635376], "messages_sent": [50508, 4828, 4366, 1974, 1898, 975, 972, 840, 742, 574], "name": ["dbaxps", "mpetason", "smaffulli", "9lives", "SamYaple", "vinoth", "mickt", "Haneef Ali", "teju", "SGPJ"]}, "participants.last year": {"id": [630911, 635376, 630994, 630817, 631088, 630928, 630918, 1755, 631114, 630938], "messages_sent": [279258, 51004, 37296, 29232, 25228, 24236, 18038, 16800, 7802, 6954], "name": ["dbaxps", "SGPJ", "smaffulli", "larsks", "mpetason", "SamYaple", "Shankar Ganesh P J", "Haneef Ali", "9lives", "Antonio G."]}, "qsenders.": {"id": [2513, 1825, 1366, 2571, 7609, 3070, 910, 6560, 2894, 3080], "senders": ["dbaxps", "vinoth", "RHK", "teju", "mickt", "SGPJ", "ebyenjoys", "amitabh sinha", "9lives", "Krist"], "sent": [7137, 2340, 1728, 1643, 1512, 1476, 1363, 1320, 846, 810]}, "qsenders.last month": {"id": [2513, 7609, 2571, 6560, 8656, 3323, 8735, 8436, 2894, 7932], "senders": ["dbaxps", "mickt", "teju", "amitabh sinha", "Pradip", "akshik", "splucena", "patrickt33", "9lives", "agm123"], "sent": [549, 270, 265, 220, 187, 161, 136, 114, 94, 90]}, "qsenders.last year": {"id": [2513, 1825, 2571, 7609, 3070, 6560, 1366, 910, 2894, 3080], "senders": ["dbaxps", "vinoth", "teju", "mickt", "SGPJ", "amitabh sinha", "RHK", "ebyenjoys", "9lives", "Krist"], "sent": [7137, 2145, 1643, 1512, 1476, 1320, 1224, 870, 846, 810]}}