{"actions": 7230, "added_lines": 194938.0, "added_lines_30": 66612, "added_lines_365": 8208106, "added_lines_7": 5004, "authors": 116, "authors_30": 5, "authors_365": 83, "authors_7": 0, "avg_commits_author": 14.1897, "avg_commits_month": 96.8235, "avg_files_author": 29.1121, "avg_files_month": 198.6471, "branches": 16, "commits": 1646, "commits_30": 15, "commits_365": 840, "commits_7": 0, "committers": 114, "diff_netadded_lines_30": -211360, "diff_netadded_lines_365": 2029626, "diff_netadded_lines_7": -4895, "diff_netauthors_30": -9, "diff_netauthors_365": -27, "diff_netauthors_7": -2, "diff_netcommits_30": -18, "diff_netcommits_365": -688, "diff_netcommits_7": -5, "diff_netfiles_30": -76, "diff_netfiles_365": -530, "diff_netfiles_7": -8, "diff_netremoved_lines_30": -158502, "diff_netremoved_lines_365": 6138420, "diff_netremoved_lines_7": 9697, "files": 3377, "files_30": 32, "files_365": 2084, "files_7": 0, "first_date": "2013-04-15", "last_date": "2014-10-02", "percentage_added_lines_30": 76, "percentage_added_lines_365": 32, "percentage_added_lines_7": 49, "percentage_authors_30": 64, "percentage_authors_365": 24, "percentage_authors_7": 100, "percentage_commits_30": 54, "percentage_commits_365": 45, "percentage_commits_7": 100, "percentage_files_30": 70, "percentage_files_365": 20, "percentage_files_7": 100, "percentage_removed_lines_30": 76, "percentage_removed_lines_365": 169, "percentage_removed_lines_7": 133, "removed_lines": 324992.0, "removed_lines_30": 49170, "removed_lines_365": 9752143, "removed_lines_7": 16947, "repositories": 20}