{"actions": 5078, "added_lines": 152246.0, "added_lines_30": 2317, "added_lines_365": 4315628, "added_lines_7": 246, "authors": 99, "authors_30": 0, "authors_365": 69, "authors_7": 0, "avg_commits_author": 11.9495, "avg_commits_month": 78.8667, "avg_files_author": 23.4242, "avg_files_month": 154.6, "branches": 14, "commits": 1183, "commits_30": 0, "commits_365": 584, "commits_7": 0, "committers": 97, "diff_netadded_lines_30": -20273, "diff_netadded_lines_365": -607589, "diff_netadded_lines_7": 107, "diff_netauthors_30": -4, "diff_netauthors_365": -35, "diff_netauthors_7": 0, "diff_netcommits_30": -10, "diff_netcommits_365": -912, "diff_netcommits_7": 0, "diff_netfiles_30": -77, "diff_netfiles_365": -1184, "diff_netfiles_7": 0, "diff_netremoved_lines_30": -15364, "diff_netremoved_lines_365": -622012, "diff_netremoved_lines_7": -77, "files": 2319, "files_30": 0, "files_365": 1279, "files_7": 0, "first_date": "2013-04-15", "last_date": "2014-08-21", "percentage_added_lines_30": 89, "percentage_added_lines_365": 12, "percentage_added_lines_7": 76, "percentage_authors_30": 100, "percentage_authors_365": 33, "percentage_authors_7": 0, "percentage_commits_30": 100, "percentage_commits_365": 60, "percentage_commits_7": 0, "percentage_files_30": 100, "percentage_files_365": 48, "percentage_files_7": 0, "percentage_removed_lines_30": 96, "percentage_removed_lines_365": 19, "percentage_removed_lines_7": 92, "removed_lines": 91012.0, "removed_lines_30": 519, "removed_lines_365": 2553915, "removed_lines_7": 6, "repositories": 20}