{"diff_netsenders_30": -7, "diff_netsenders_365": 29, "diff_netsenders_7": -2, "diff_netsent_30": -19, "diff_netsent_365": 482, "diff_netsent_7": -5, "first_date": "2013-04-17", "last_date": "2014-11-14", "percentage_senders_30": 36, "percentage_senders_365": 111, "percentage_senders_7": 33, "percentage_sent_30": 26, "percentage_sent_365": 303, "percentage_sent_7": 38, "repositories": 1, "senders": 64, "senders_30": 12, "senders_365": 55, "senders_7": 4, "senders_init": 22, "senders_response": 62, "sent": 800, "sent_30": 53, "sent_365": 641, "sent_7": 8, "sent_response": 584, "threads": 216}