{"actions": 41716, "added_lines": 1313703.0, "added_lines_30": 30748, "added_lines_365": 10760438, "added_lines_7": 1840, "authors": 149, "authors_30": 39, "authors_365": 145, "authors_7": 7, "avg_commits_author": 65.396, "avg_commits_month": 541.3333, "avg_files_author": 137.1611, "avg_files_month": 1135.3889, "branches": 44, "commits": 9744, "commits_30": 187, "commits_365": 6473, "commits_7": 9, "committers": 144, "diff_netadded_lines_30": -361403, "diff_netadded_lines_365": 972492, "diff_netadded_lines_7": -3931, "diff_netauthors_30": -41, "diff_netauthors_365": 55, "diff_netauthors_7": -7, "diff_netcommits_30": -356, "diff_netcommits_365": 1244, "diff_netcommits_7": -62, "diff_netfiles_30": -3595, "diff_netfiles_365": 2752, "diff_netfiles_7": -227, "diff_netremoved_lines_30": -340498, "diff_netremoved_lines_365": 7066711, "diff_netremoved_lines_7": -2925, "files": 20437, "files_30": 653, "files_365": 13442, "files_7": 10, "first_date": "2013-04-15", "last_date": "2014-11-10", "percentage_added_lines_30": 92, "percentage_added_lines_365": 9, "percentage_added_lines_7": 68, "percentage_authors_30": 51, "percentage_authors_365": 61, "percentage_authors_7": 50, "percentage_commits_30": 65, "percentage_commits_365": 23, "percentage_commits_7": 87, "percentage_files_30": 84, "percentage_files_365": 25, "percentage_files_7": 95, "percentage_removed_lines_30": 98, "percentage_removed_lines_365": 118, "percentage_removed_lines_7": 99, "removed_lines": 1122379.0, "removed_lines_30": 6157, "removed_lines_365": 13043761, "removed_lines_7": 27, "repositories": 82}