{"authors.": {"authors": ["Jenkins", "OpenStack Jenkins", "Dan Smith", "Brant Knudson", "Steve Baker", "Steven Hardy", "Gary Kotton", "Zane Bitter", "Angus Salkeld", "Dan Prince"], "commits": [6464.0, 630.0, 394.0, 364.0, 348.0, 328.0, 301.0, 284.0, 271.0, 271.0], "id": [26, 136, 606, 645, 641, 714, 49, 1212, 716, 106]}, "authors.last month": {"authors": ["Jenkins", "Martina Kollarova", "Morgan Fainberg", "OpenStack Proposal Bot", "Ghanshyam Mann", "Ken'ichi Ohmichi", "Brant Knudson", "Christopher Yeoh", "Alan Pevec", "He Jie Xu"], "commits": [294.0, 41.0, 23.0, 22.0, 19.0, 18.0, 17.0, 17.0, 16.0, 14.0], "id": [26, 643, 395, 862, 755, 383, 645, 369, 126, 103]}, "authors.last year": {"authors": ["Jenkins", "OpenStack Jenkins", "Brant Knudson", "Dan Smith", "Gary Kotton", "Steven Hardy", "OpenStack Proposal Bot", "Jason Guiditta", "Steve Baker", "Crag Wolfe"], "commits": [4695.0, 387.0, 311.0, 273.0, 249.0, 243.0, 230.0, 225.0, 211.0, 205.0], "id": [26, 136, 645, 606, 49, 714, 862, 908, 641, 909]}}