{"actions": 136126, "added_lines": 13149489.0, "added_lines_30": 69593, "added_lines_365": 8516138, "added_lines_7": 807, "authors": 1506, "authors_30": 133, "authors_365": 1271, "authors_7": 13, "avg_commits_author": 20.6361, "avg_commits_month": 1824.4706, "avg_files_author": 16.6121, "avg_files_month": 1468.7059, "branches": 29, "commits": 31016, "commits_30": 494, "commits_365": 20996, "commits_7": 34, "committers": 1475, "companies": 130, "core": 207, "diff_netadded_lines_30": -181507, "diff_netadded_lines_365": 2681893, "diff_netadded_lines_7": -248, "diff_netauthors_30": -267, "diff_netauthors_365": 352, "diff_netauthors_7": -8, "diff_netcommits_30": -1418, "diff_netcommits_365": 2301, "diff_netcommits_7": -6, "diff_netfiles_30": -2608, "diff_netfiles_365": 2303, "diff_netfiles_7": 9, "diff_netremoved_lines_30": -166808, "diff_netremoved_lines_365": 6441665, "diff_netremoved_lines_7": -294, "files": 24968, "files_30": 1273, "files_365": 18555, "files_7": 63, "first_date": "2013-04-15", "last_date": "2014-09-26", "occasional": 879, "percentage_added_lines_30": 72, "percentage_added_lines_365": 45, "percentage_added_lines_7": 23, "percentage_authors_30": 66, "percentage_authors_365": 38, "percentage_authors_7": 38, "percentage_commits_30": 74, "percentage_commits_365": 12, "percentage_commits_7": 15, "percentage_files_30": 67, "percentage_files_365": 14, "percentage_files_7": 16, "percentage_removed_lines_30": 86, "percentage_removed_lines_365": 186, "percentage_removed_lines_7": 65, "regular": 417, "removed_lines": 12532579.0, "removed_lines_30": 26427, "removed_lines_365": 9887821, "removed_lines_7": 158, "repositories": 54, "type": "git", "url": "https://github.com/redhat-openstack/quantum.git"}