{"actions": 78907, "added_lines": 7533201.0, "added_lines_30": 5083, "added_lines_365": 4727543, "added_lines_7": 1072, "authors": 985, "authors_30": 43, "authors_365": 792, "authors_7": 9, "avg_commits_author": 18.2159, "avg_commits_month": 1192.5333, "avg_files_author": 16.1823, "avg_files_month": 1059.4, "branches": 27, "commits": 17888, "commits_30": 133, "commits_365": 11902, "commits_7": 15, "committers": 958, "companies": 125, "core": 160, "diff_netadded_lines_30": -13355, "diff_netadded_lines_365": 150326, "diff_netadded_lines_7": 513, "diff_netauthors_30": -22, "diff_netauthors_365": -43, "diff_netauthors_7": -3, "diff_netcommits_30": -166, "diff_netcommits_365": -5084, "diff_netcommits_7": -8, "diff_netfiles_30": -196, "diff_netfiles_365": -3135, "diff_netfiles_7": -27, "diff_netremoved_lines_30": -14155, "diff_netremoved_lines_365": -23348, "diff_netremoved_lines_7": -22, "files": 15891, "files_30": 207, "files_365": 11357, "files_7": 20, "first_date": "2013-04-15", "last_date": "2014-08-01", "occasional": 531, "percentage_added_lines_30": 72, "percentage_added_lines_365": 3, "percentage_added_lines_7": 91, "percentage_authors_30": 33, "percentage_authors_365": 5, "percentage_authors_7": 25, "percentage_commits_30": 55, "percentage_commits_365": 29, "percentage_commits_7": 34, "percentage_files_30": 48, "percentage_files_365": 21, "percentage_files_7": 57, "percentage_removed_lines_30": 85, "percentage_removed_lines_365": 0, "percentage_removed_lines_7": 12, "regular": 291, "removed_lines": 4574848.0, "removed_lines_30": 2346, "removed_lines_365": 2870630, "removed_lines_7": 154, "repositories": 54, "type": "git", "url": "https://github.com/redhat-openstack/quantum.git"}