{"actions": 145441, "added_lines": 13443168.0, "added_lines_30": 80169, "added_lines_365": 7816185, "added_lines_7": 327, "authors": 1589, "authors_30": 128, "authors_365": 1320, "authors_7": 8, "avg_commits_author": 21.0069, "avg_commits_month": 1850.9444, "avg_files_author": 17.1488, "avg_files_month": 1511.0, "branches": 33, "commits": 33317, "commits_30": 404, "commits_365": 21422, "commits_7": 12, "committers": 1552, "companies": 153, "core": 214, "diff_netadded_lines_30": -214463, "diff_netadded_lines_365": 1214563, "diff_netadded_lines_7": -5728, "diff_netauthors_30": -303, "diff_netauthors_365": 375, "diff_netauthors_7": -17, "diff_netcommits_30": -1735, "diff_netcommits_365": 1688, "diff_netcommits_7": -44, "diff_netfiles_30": -2443, "diff_netfiles_365": 2874, "diff_netfiles_7": -161, "diff_netremoved_lines_30": -1105, "diff_netremoved_lines_365": 5995699, "diff_netremoved_lines_7": -1053, "files": 27198, "files_30": 1906, "files_365": 19906, "files_7": 12, "first_date": "2013-04-15", "last_date": "2014-10-24", "occasional": 928, "percentage_added_lines_30": 72, "percentage_added_lines_365": 18, "percentage_added_lines_7": 94, "percentage_authors_30": 70, "percentage_authors_365": 39, "percentage_authors_7": 68, "percentage_commits_30": 81, "percentage_commits_365": 8, "percentage_commits_7": 78, "percentage_files_30": 56, "percentage_files_365": 16, "percentage_files_7": 93, "percentage_removed_lines_30": 0, "percentage_removed_lines_365": 160, "percentage_removed_lines_7": 96, "regular": 444, "removed_lines": 12859668.0, "removed_lines_30": 177382, "removed_lines_365": 9727434, "removed_lines_7": 33, "repositories": 54, "type": "git", "url": "https://github.com/redhat-openstack/quantum.git"}