{"actions": 226712, "added_lines": 19649628.0, "added_lines_30": 283818, "added_lines_365": 10480031, "added_lines_7": 144810, "authors": 1824, "authors_30": 64, "authors_365": 1520, "authors_7": 25, "avg_commits_author": 27.3661, "avg_commits_month": 2624.2632, "avg_files_author": 27.1734, "avg_files_month": 2605.7895, "branches": 51, "commits": 49861, "commits_30": 315, "commits_365": 31311, "commits_7": 85, "committers": 1773, "companies": 153, "core": 249, "diff_netadded_lines_30": -10954, "diff_netadded_lines_365": 225456, "diff_netadded_lines_7": 137261, "diff_netauthors_30": -225, "diff_netauthors_365": 453, "diff_netauthors_7": -5, "diff_netcommits_30": -882, "diff_netcommits_365": 4091, "diff_netcommits_7": -5, "diff_netfiles_30": -1047, "diff_netfiles_365": 9627, "diff_netfiles_7": 2125, "diff_netremoved_lines_30": -269336, "diff_netremoved_lines_365": 6778555, "diff_netremoved_lines_7": 881, "files": 49510, "files_30": 4744, "files_365": 36034, "files_7": 2354, "first_date": "2013-04-15", "last_date": "2014-11-22", "occasional": 1095, "percentage_added_lines_30": 3, "percentage_added_lines_365": 2, "percentage_added_lines_7": 1818, "percentage_authors_30": 77, "percentage_authors_365": 42, "percentage_authors_7": 16, "percentage_commits_30": 73, "percentage_commits_365": 15, "percentage_commits_7": 5, "percentage_files_30": 18, "percentage_files_365": 36, "percentage_files_7": 927, "percentage_removed_lines_30": 97, "percentage_removed_lines_365": 111, "percentage_removed_lines_7": 81, "regular": 478, "removed_lines": 18369522.0, "removed_lines_30": 6406, "removed_lines_365": 12879035, "removed_lines_7": 1959, "repositories": 83, "type": "git", "url": "https://github.com/redhat-openstack/quantum.git"}