{"actions": 260, "added_lines": 14816.0, "added_lines_30": 52401, "added_lines_365": 8893175, "added_lines_7": 2552, "authors": 9, "authors_30": 0, "authors_365": 4, "authors_7": 0, "avg_commits_author": 8.4444, "avg_commits_month": 5.4286, "avg_files_author": 25.4444, "avg_files_month": 16.3571, "branches": 8, "commits": 76, "commits_30": 0, "commits_365": 25, "commits_7": 0, "committers": 9, "diff_netadded_lines_30": -70862, "diff_netadded_lines_365": 3508736, "diff_netadded_lines_7": -15570, "diff_netauthors_30": -1, "diff_netauthors_365": -6, "diff_netauthors_7": 0, "diff_netcommits_30": -1, "diff_netcommits_365": -94, "diff_netcommits_7": 0, "diff_netfiles_30": -1, "diff_netfiles_365": -184, "diff_netfiles_7": 0, "diff_netremoved_lines_30": -26407, "diff_netremoved_lines_365": 6697829, "diff_netremoved_lines_7": -11105, "files": 229, "files_30": 0, "files_365": 91, "files_7": 0, "first_date": "2013-04-15", "last_date": "2014-09-09", "percentage_added_lines_30": 57, "percentage_added_lines_365": 65, "percentage_added_lines_7": 85, "percentage_authors_30": 100, "percentage_authors_365": 60, "percentage_authors_7": 0, "percentage_commits_30": 100, "percentage_commits_365": 78, "percentage_commits_7": 0, "percentage_files_30": 100, "percentage_files_365": 66, "percentage_files_7": 0, "percentage_removed_lines_30": 45, "percentage_removed_lines_365": 204, "percentage_removed_lines_7": 92, "removed_lines": 6173.0, "removed_lines_30": 31645, "removed_lines_365": 9975089, "removed_lines_7": 860, "repositories": 12}